arucosheet/__init__.py
arucosheet/cli.py
arucosheet-1.1.0.dist-info/licenses/LICENSE
arucosheet-1.1.0.dist-info/METADATA
arucosheet-1.1.0.dist-info/WHEEL
arucosheet-1.1.0.dist-info/entry_points.txt
arucosheet-1.1.0.dist-info/top_level.txt
arucosheet-1.1.0.dist-info/RECORD
