Metadata-Version: 2.4
Name: ArucoSheet
Version: 1.1.0
Summary: A powerful command-line tool to generate customizable, print-ready PDF sheets of ArUco markers.
Author-email: Giuliano Ranauro <ranaurogln@email.com>
License:                     GNU GENERAL PUBLIC LICENSE
Project-URL: Homepage, https://github.com/follen99/ArucoSheet
Project-URL: Issues, https://github.com/follen99/ArUcoSheet/issues
Classifier: Programming Language :: Python :: 3
Classifier: License :: OSI Approved :: GNU General Public License v3 (GPLv3)
Classifier: Operating System :: OS Independent
Classifier: Topic :: Scientific/Engineering :: Image Recognition
Requires-Python: >=3.7
License-File: LICENSE
Requires-Dist: opencv-contrib-python
Requires-Dist: numpy
Requires-Dist: Pillow
Dynamic: license-file
